filesize_from_stdin/__init__.py
filesize_from_stdin/cli.py
filesize_from_stdin/filesize_from_stdin.py
filesize_from_stdin-1.0.6.dist-info/AUTHORS.rst
filesize_from_stdin-1.0.6.dist-info/LICENSE
filesize_from_stdin-1.0.6.dist-info/METADATA
filesize_from_stdin-1.0.6.dist-info/WHEEL
filesize_from_stdin-1.0.6.dist-info/entry_points.txt
filesize_from_stdin-1.0.6.dist-info/top_level.txt
filesize_from_stdin-1.0.6.dist-info/RECORD
