Metadata-Version: 2.1
Name: filesize-from-stdin
Version: 1.0.6
Summary: Given a list of files one-per-line, show the file size followed by space and then file path
Home-page: https://github.com/taylormonacelli/filesize_from_stdin
Author: Taylor Monacelli
Author-email: taylormonacelli@gmail.com
License: MIT license
Keywords: filesize_from_stdin
Platform: UNKNOWN
Classifier: Development Status :: 2 - Pre-Alpha
Classifier: Intended Audience :: Developers
Classifier: License :: OSI Approved :: MIT License
Classifier: Natural Language :: English
Classifier: Programming Language :: Python :: 2
Classifier: Programming Language :: Python :: 2.7
Classifier: Programming Language :: Python :: 3
Classifier: Programming Language :: Python :: 3.4
Classifier: Programming Language :: Python :: 3.5
Classifier: Programming Language :: Python :: 3.6
Classifier: Programming Language :: Python :: 3.7
Requires-Dist: Click (<8.0)
Requires-Dist: pathlib (<2.0)
Requires-Dist: humanize (<=1.0)
